simple_hierarchy/__init__.py
simple_hierarchy/examples/sample.ipynb
simple_hierarchy/hierarchal_model.py
simple_hierarchy/tree.py
simple_hierarchy-1.0.2.dist-info/LICENSE
simple_hierarchy-1.0.2.dist-info/WHEEL
simple_hierarchy-1.0.2.dist-info/METADATA
simple_hierarchy-1.0.2.dist-info/RECORD
