Metadata-Version: 2.1
Name: simple-hierarchy
Version: 1.0.2
Summary: Simple hierarchal models in PyTorch.
Home-page: https://github.com/rajivsarvepalli/SimpleHierarchy
License: MIT
Keywords: pytorch,hierarchical-models,neural-network,machine-learning,hierarchal-networks,python,pytorch hierarchy networks,pytorch cnn,cnn hierarchy,hierarchy networks,simple hierarchy,pytorch hierarchy,torch hierarchy,torch cnn
Author: Rajiv Sarvepalli
Author-email: rajiv@sarvepalli.net
Requires-Python: >=3.7,<4.0
Classifier: License :: OSI Approved :: MIT License
Classifier: Operating System :: OS Independent
Classifier: Programming Language :: Python :: 3
Classifier: Programming Language :: Python :: 3.7
Classifier: Programming Language :: Python :: 3.8
Requires-Dist: importlib-metadata (>=3.3.0,<4.0.0); python_version < "3.8"
Requires-Dist: numpy (==1.19.3)
Requires-Dist: torch (>=1.7.0,<2.0.0); python_version >= "3.7" and python_version < "4.0"
Project-URL: Documentation, https://simplehierarchy.readthedocs.io
Project-URL: Repository, https://github.com/rajivsarvepalli/SimpleHierarchy
